core/__init__.py
core/auth.py
core/azure_token_manager.py
core/bpa_analyzer.py
core/bpa_service.py
prompts/__init__.py
prompts/mcp_prompts.py
semantic_model_mcp_server-0.3.0.dist-info/licenses/LICENSE
src/helper.py
src/tmsl_validator.py
tools/bpa_tools.py
tools/dax_local_explorer.py
tools/fabric_metadata.py
tools/fast_powerbi_detector.py
tools/improved_dax_explorer.py
tools/local_powerbi_explorer.py
tools/microsoft_learn.py
tools/microsoft_learn_tools.py
tools/powerbi_desktop_detector.py
tools/powerbi_desktop_tools.py
tools/simple_dax_explorer.py
tools/ultra_fast_powerbi_detector.py
semantic_model_mcp_server-0.3.0.dist-info/METADATA
semantic_model_mcp_server-0.3.0.dist-info/WHEEL
semantic_model_mcp_server-0.3.0.dist-info/entry_points.txt
semantic_model_mcp_server-0.3.0.dist-info/top_level.txt
semantic_model_mcp_server-0.3.0.dist-info/RECORD
