Metadata-Version: 2.4
Name: semantic-model-mcp-server
Version: 0.3.0
Summary: A Model Context Protocol server for Microsoft Fabric and Power BI semantic models
Author-email: Microsoft Fabric Toolbox <fabric-toolbox@company.com>
Maintainer-email: Microsoft Fabric Toolbox <fabric-toolbox@company.com>
License: MIT
Project-URL: Homepage, https://github.com/nahtheking/semantic-model-mcp
Project-URL: Repository, https://github.com/nahtheking/semantic-model-mcp
Project-URL: Documentation, https://github.com/nahtheking/semantic-model-mcp/blob/main/readme.md
Project-URL: Issues, https://github.com/nahtheking/semantic-model-mcp/issues
Keywords: powerbi,fabric,semantic-model,mcp,model-context-protocol,dax,tmsl,analysis-services,best-practices-analyzer
Classifier: Development Status :: 4 - Beta
Classifier: Intended Audience :: Developers
Classifier: License :: OSI Approved :: MIT License
Classifier: Programming Language :: Python :: 3
Classifier: Programming Language :: Python :: 3.8
Classifier: Programming Language :: Python :: 3.9
Classifier: Programming Language :: Python :: 3.10
Classifier: Programming Language :: Python :: 3.11
Classifier: Programming Language :: Python :: 3.12
Classifier: Topic :: Software Development :: Libraries :: Python Modules
Classifier: Topic :: Office/Business :: Financial :: Spreadsheet
Classifier: Operating System :: Microsoft :: Windows
Requires-Python: >=3.8
License-File: LICENSE
Requires-Dist: fastmcp>=0.1.0
Requires-Dist: msal>=1.24.0
Requires-Dist: requests>=2.31.0
Requires-Dist: pythonnet>=3.0.0rc6
Requires-Dist: pyodbc>=4.0.0
Requires-Dist: psutil>=5.9.0
Requires-Dist: urllib3>=2.0.0
Requires-Dist: azure-identity
Provides-Extra: dev
Requires-Dist: pytest>=7.0.0; extra == "dev"
Requires-Dist: black>=23.0.0; extra == "dev"
Requires-Dist: pylint>=2.17.0; extra == "dev"
Requires-Dist: mypy>=1.0.0; extra == "dev"
Provides-Extra: test
Requires-Dist: pytest>=7.0.0; extra == "test"
Requires-Dist: pytest-cov>=4.0.0; extra == "test"
Dynamic: license-file
